CHANGELOG.rst
LICENSE.txt
MANIFEST.in
README.rst
setup.py
bin/zeo_connector_gen_defaults.py
src/zeo_connector_defaults/__init__.py
src/zeo_connector_defaults/environment_generator.py
src/zeo_connector_defaults.egg-info/PKG-INFO
src/zeo_connector_defaults.egg-info/SOURCES.txt
src/zeo_connector_defaults.egg-info/dependency_links.txt
src/zeo_connector_defaults.egg-info/not-zip-safe
src/zeo_connector_defaults.egg-info/top_level.txt
src/zeo_connector_defaults/default_data/zeo.conf
src/zeo_connector_defaults/default_data/zeo_client.conf
src/zeo_connector_defaults/template_data/zeo.conf
src/zeo_connector_defaults/template_data/zeo_client.conf