Metadata-Version: 1.1
Name: zeo-connector-defaults
Version: 0.2.2
Summary: Default conf. files and conf. file generator for `zeo_connector`.
Home-page: https://github.com/Bystroushaak/zeo_connector_defaults
Author: Bystroushaak
Author-email: bystrousak@kitakitsune.org
License: MIT
Platform: UNKNOWN
Classifier: Development Status :: 4 - Beta
Classifier: Intended Audience :: Developers
Classifier: Programming Language :: Python :: 2
Classifier: Programming Language :: Python :: 2.7
Classifier: License :: OSI Approved :: MIT License
